[
  {
    "timestamp_iso": "2025-11-04T21:35:23.088000",
    "timestamp_unix": 1762310123.088,
    "participant": "P20251104213521_bbe2fc",
    "scenario": 1,
    "condition": 2,
    "frame": 0,
    "type": "message_click",
    "message_id": "robot2-7.47",
    "action": "opened"
  },
  {
    "timestamp_iso": "2025-11-04T21:35:23.818000",
    "timestamp_unix": 1762310123.818,
    "participant": "P20251104213521_bbe2fc",
    "scenario": 1,
    "condition": 2,
    "frame": 0,
    "type": "message_click",
    "message_id": "robot1-7.47",
    "action": "opened"
  },
  {
    "timestamp_iso": "2025-11-04T21:35:24.540000",
    "timestamp_unix": 1762310124.54,
    "participant": "P20251104213521_bbe2fc",
    "scenario": 1,
    "condition": 2,
    "frame": 1,
    "type": "message_click",
    "message_id": "robot3-7.47",
    "action": "opened"
  },
  {
    "timestamp_iso": "2025-11-04T21:35:28.776000",
    "timestamp_unix": 1762310128.776,
    "participant": "P20251104213521_bbe2fc",
    "scenario": 1,
    "condition": 2,
    "frame": 4,
    "type": "message_click",
    "message_id": "robot1-27.47",
    "action": "opened"
  },
  {
    "timestamp_iso": "2025-11-04T21:35:29.143000",
    "timestamp_unix": 1762310129.143,
    "participant": "P20251104213521_bbe2fc",
    "scenario": 1,
    "condition": 2,
    "frame": 4,
    "type": "message_click",
    "message_id": "robot2-27.47",
    "action": "opened"
  },
  {
    "timestamp_iso": "2025-11-04T21:35:30.001000",
    "timestamp_unix": 1762310130.001,
    "participant": "P20251104213521_bbe2fc",
    "scenario": 1,
    "condition": 2,
    "frame": 5,
    "type": "message_click",
    "message_id": "robot3-27.47",
    "action": "opened"
  },
  {
    "timestamp_iso": "2025-11-04T21:35:31.212000",
    "timestamp_unix": 1762310131.212,
    "participant": "P20251104213521_bbe2fc",
    "scenario": 1,
    "condition": 2,
    "frame": 5,
    "type": "message_click",
    "message_id": "robot1-32.47",
    "action": "opened"
  },
  {
    "timestamp_iso": "2025-11-04T21:35:31.928000",
    "timestamp_unix": 1762310131.928,
    "participant": "P20251104213521_bbe2fc",
    "scenario": 1,
    "condition": 2,
    "frame": 5,
    "type": "message_click",
    "message_id": "robot2-32.47",
    "action": "opened"
  },
  {
    "timestamp_iso": "2025-11-04T21:35:32.847000",
    "timestamp_unix": 1762310132.847,
    "participant": "P20251104213521_bbe2fc",
    "scenario": 1,
    "condition": 2,
    "frame": 6,
    "type": "message_click",
    "message_id": "robot3-34.10",
    "action": "opened"
  },
  {
    "timestamp_iso": "2025-11-04T21:35:36.233000",
    "timestamp_unix": 1762310136.233,
    "participant": "P20251104213521_bbe2fc",
    "scenario": 1,
    "condition": 2,
    "frame": 8,
    "type": "message_click",
    "message_id": "robot2-36.60",
    "action": "opened"
  }
]